ephyalign/__init__.py
ephyalign/cli.py
ephyalign/config.py
ephyalign/pipeline.py
ephyalign/core/__init__.py
ephyalign/core/aligner.py
ephyalign/core/detector.py
ephyalign/core/filters.py
ephyalign/core/loader.py
ephyalign/core/metrics.py
ephyalign/io/__init__.py
ephyalign/io/exporters.py
ephyalign/io/paths.py
ephyalign/visualization/__init__.py
ephyalign/visualization/plots.py
ephyalign-0.1.0.dist-info/METADATA
ephyalign-0.1.0.dist-info/WHEEL
ephyalign-0.1.0.dist-info/entry_points.txt
ephyalign-0.1.0.dist-info/licenses/LICENSE
ephyalign-0.1.0.dist-info/RECORD
