Metadata-Version: 2.4
Name: ephyalign
Version: 0.1.0
Summary: Electrophysiology Response Alignment Toolkit - Automatically detect and align stimulus-evoked responses in ABF recordings with sub-millisecond precision
Project-URL: Homepage, https://github.com/yourusername/ephyalign
Project-URL: Documentation, https://ephyalign.readthedocs.io
Project-URL: Repository, https://github.com/yourusername/ephyalign.git
Project-URL: Issues, https://github.com/yourusername/ephyalign/issues
Project-URL: Changelog, https://github.com/yourusername/ephyalign/blob/main/CHANGELOG.md
Author: Samuel Matthews Mckay Loureiro
License: MIT
License-File: LICENSE
Keywords: abf,alignment,axon,electrophysiology,epoch,neuroscience,signal-processing,stimfit,stimulus
Classifier: Development Status :: 4 - Beta
Classifier: Intended Audience :: Science/Research
Classifier: License :: OSI Approved :: MIT License
Classifier: Operating System :: OS Independent
Classifier: Programming Language :: Python :: 3
Classifier: Programming Language :: Python :: 3.10
Classifier: Programming Language :: Python :: 3.11
Classifier: Programming Language :: Python :: 3.12
Classifier: Topic :: Scientific/Engineering :: Bio-Informatics
Classifier: Topic :: Scientific/Engineering :: Medical Science Apps.
Classifier: Typing :: Typed
Requires-Python: >=3.10
Requires-Dist: click>=8.1.0
Requires-Dist: h5py>=3.8.0
Requires-Dist: matplotlib>=3.7.0
Requires-Dist: numpy>=1.24.0
Requires-Dist: pyabf>=2.3.8
Requires-Dist: tables>=3.8.0
Provides-Extra: all
Requires-Dist: black>=23.0; extra == 'all'
Requires-Dist: isort>=5.12; extra == 'all'
Requires-Dist: mypy>=1.0; extra == 'all'
Requires-Dist: pre-commit>=3.0; extra == 'all'
Requires-Dist: pytest-cov>=4.0; extra == 'all'
Requires-Dist: pytest>=7.0; extra == 'all'
Requires-Dist: pyyaml>=6.0; extra == 'all'
Requires-Dist: ruff>=0.1.0; extra == 'all'
Requires-Dist: sphinx-click>=4.0; extra == 'all'
Requires-Dist: sphinx-rtd-theme>=1.0; extra == 'all'
Requires-Dist: sphinx>=6.0; extra == 'all'
Provides-Extra: build
Requires-Dist: build>=1.0; extra == 'build'
Requires-Dist: twine>=4.0; extra == 'build'
Provides-Extra: dev
Requires-Dist: black>=23.0; extra == 'dev'
Requires-Dist: isort>=5.12; extra == 'dev'
Requires-Dist: mypy>=1.0; extra == 'dev'
Requires-Dist: pre-commit>=3.0; extra == 'dev'
Requires-Dist: pytest-cov>=4.0; extra == 'dev'
Requires-Dist: pytest>=7.0; extra == 'dev'
Requires-Dist: ruff>=0.1.0; extra == 'dev'
Provides-Extra: docs
Requires-Dist: sphinx-click>=4.0; extra == 'docs'
Requires-Dist: sphinx-rtd-theme>=1.0; extra == 'docs'
Requires-Dist: sphinx>=6.0; extra == 'docs'
Provides-Extra: yaml
Requires-Dist: pyyaml>=6.0; extra == 'yaml'
